{"type":"FeatureCollection","features":[{"type":"Feature","properties":{"buildingname":"Athletics Centre"},"geometry":{"coordinates":[-79.40103520574223,43.66275758078362],"type":"Point"}},{"type":"Feature","properties":{"buildingname":"Hart House"},"geometry":{"coordinates":[-79.39396438850243,43.66393311249655],"type":"Point"}}]}